ui/__init__.py
ui/cli.py
ui/core/__init__.py
ui/core/app.py
ui/core/app_controller.py
ui/core/command_bus.py
ui/core/frameless_window.py
ui/core/interface_ports.py
ui/core/main.py
ui/core/router.py
ui/core/settings.py
ui/core/theme_service.py
ui/core/toast_manager.py
ui/core/utils/factories.py
ui/core/utils/guard.py
ui/core/utils/paths.py
ui/dialogs/quick_open.py
ui/services/__init__.py
ui/services/qss_renderer.py
ui/services/task_runner_adapter.py
ui/services/theme_repository_json.py
ui/splash/__init__.py
ui/splash/splash.py
ui/widgets/__init__.py
ui/widgets/async_button.py
ui/widgets/buttons.py
ui/widgets/loading_overlay.py
ui/widgets/overlay_sidebar.py
ui/widgets/push_sidebar.py
ui/widgets/settings_sidebar.py
ui/widgets/titlebar.py
ui/widgets/toast.py
ui/widgets/topbar.py
ui_fram_skk-0.1.1.dist-info/licenses/license
ui_fram_skk-0.1.1.dist-info/METADATA
ui_fram_skk-0.1.1.dist-info/WHEEL
ui_fram_skk-0.1.1.dist-info/entry_points.txt
ui_fram_skk-0.1.1.dist-info/top_level.txt
ui_fram_skk-0.1.1.dist-info/RECORD
