Metadata-Version: 2.4
Name: ui-fram-skk
Version: 0.1.1
Summary: Framework de UI desktop (PySide6) com janela frameless, roteamento e temas
Author-email: João Vitor de Souza Siqueira <skkiler13ka@gmail.com>
License: Copyright 2025 João Vitor de Souza Siqueira
Project-URL: Homepage, https://github.com/Skkiler/framework-pyside6
Project-URL: Repository, https://github.com/Skkiler/framework-pyside6
Keywords: pyside6,qt,ui,desktop,framework
Classifier: Programming Language :: Python :: 3
Classifier: Programming Language :: Python :: 3 :: Only
Classifier: Programming Language :: Python :: 3.10
Classifier: License :: OSI Approved :: MIT License
Classifier: Operating System :: OS Independent
Classifier: Environment :: Win32 (MS Windows)
Classifier: Topic :: Software Development :: User Interfaces
Requires-Python: >=3.10
License-File: license
Requires-Dist: PySide6
Dynamic: license-file
